dora_arm_so101/calibrate.py
dora_arm_so101/keybord.py
dora_arm_so101/main.py
dora_arm_so101/print_joint.py
dora_arm_so101/motors/__init__.py
dora_arm_so101/motors/calibration_gui.py
dora_arm_so101/motors/motors_bus.py
dora_arm_so101/motors/feetech/__init__.py
dora_arm_so101/motors/feetech/feetech.py
dora_arm_so101/motors/feetech/tables.py
dora_arm_so101/motors/utils/encoding_utils.py
dora_arm_so101/motors/utils/utils.py
dora_arm_so101-0.0.2.dist-info/licenses/LICENSE
dora_arm_so101-0.0.2.dist-info/METADATA
dora_arm_so101-0.0.2.dist-info/WHEEL
dora_arm_so101-0.0.2.dist-info/entry_points.txt
dora_arm_so101-0.0.2.dist-info/top_level.txt
dora_arm_so101-0.0.2.dist-info/RECORD
