Metadata-Version: 2.4
Name: dora-arm-so101
Version: 0.0.2
Author-email: Xiang Yang <ryu-yang@qq.com>
Requires-Python: <3.14,>=3.8
License-File: LICENSE
Requires-Dist: dora-rs<0.4.0,>=0.3.11
Requires-Dist: feetech-servo-sdk>=1.0.0
Requires-Dist: numpy
Requires-Dist: pyarrow
Requires-Dist: deepdiff
Requires-Dist: tqdm
Requires-Dist: pygame
Requires-Dist: draccus
Requires-Dist: pynput
Dynamic: license-file
